medlineplus/__init__.py
medlineplus/bin/__init__.py
medlineplus/bin/_condition.py
medlineplus/bin/_gene.py
medlineplus/core/__init__.py
medlineplus/core/genetics/__init__.py
medlineplus/core/genetics/condition.py
medlineplus/core/genetics/gene.py
medlineplus/utils/__init__.py
medlineplus/version/version.json
medlineplus-1.0.2.dist-info/METADATA
medlineplus-1.0.2.dist-info/WHEEL
medlineplus-1.0.2.dist-info/entry_points.txt
medlineplus-1.0.2.dist-info/top_level.txt
medlineplus-1.0.2.dist-info/RECORD
