Metadata-Version: 2.1
Name: medlineplus
Version: 1.0.2
Summary: Genetics Home Reference(GHR) from MedlinePlus
Home-page: https://github.com/suqingdong/medlineplus
Author: suqingdong
Author-email: 1078595229@qq.com
License: BSD License
Project-URL: Documentation, https://medlineplus.readthedocs.io
Project-URL: Tracker, https://github.com/suqingdong/medlineplus/issues
Platform: UNKNOWN
Classifier: Development Status :: 5 - Production/Stable
Classifier: Operating System :: OS Independent
Classifier: Intended Audience :: Developers
Classifier: License :: OSI Approved :: BSD License
Classifier: Programming Language :: Python
Classifier: Programming Language :: Python :: 3
Classifier: Topic :: Software Development :: Libraries
Requires-Dist: click
Requires-Dist: json2xml
Requires-Dist: prettytable
Requires-Dist: webrequests
Requires-Dist: simple-loggers
